odoo/addons/portal_partner_statement/README.rst
odoo/addons/portal_partner_statement/__init__.py
odoo/addons/portal_partner_statement/__manifest__.py
odoo/addons/portal_partner_statement/controllers/__init__.py
odoo/addons/portal_partner_statement/controllers/portal.py
odoo/addons/portal_partner_statement/i18n/portal_partner_statement.pot
odoo/addons/portal_partner_statement/readme/CONTRIBUTORS.rst
odoo/addons/portal_partner_statement/readme/DESCRIPTION.rst
odoo/addons/portal_partner_statement/readme/ROADMAP.rst
odoo/addons/portal_partner_statement/readme/USAGE.rst
odoo/addons/portal_partner_statement/static/description/icon.png
odoo/addons/portal_partner_statement/static/description/index.html
odoo/addons/portal_partner_statement/tests/__init__.py
odoo/addons/portal_partner_statement/tests/test_portal.py
odoo/addons/portal_partner_statement/views/portal_views.xml
odoo14_addon_portal_partner_statement-14.0.1.0.1.dev2.dist-info/METADATA
odoo14_addon_portal_partner_statement-14.0.1.0.1.dev2.dist-info/WHEEL
odoo14_addon_portal_partner_statement-14.0.1.0.1.dev2.dist-info/top_level.txt
odoo14_addon_portal_partner_statement-14.0.1.0.1.dev2.dist-info/RECORD
